.gitattributes
.gitignore
.travis.yml
LICENSE
MANIFEST.in
NEXT.ipynb
NEXT.md
README.md
deploy.bat
deploy.sh
localdeploy.bat
requirements.tests.txt
requirements.txt
setup.cfg
setup.py
examples/files/1.xlsx
examples/files/2.xlsx
examples/files/tables.xlsx
tests/date_fns.py
tests/misc.py
utilita/__init__.py
utilita/csvmapper.py
utilita/date_fns.py
utilita/date_strs.py
utilita/dictmapper.py
utilita/excel.py
utilita/misc.py
utilita/sendgridhelper.py
utilita.egg-info/PKG-INFO
utilita.egg-info/SOURCES.txt
utilita.egg-info/dependency_links.txt
utilita.egg-info/requires.txt
utilita.egg-info/top_level.txt