Metadata-Version: 2.1
Name: utilita
Version: 1.0.14
Summary: a utility library
Home-page: https://github.com/json2d/utilita
Author: Jason Yung, Tommy Rojo
Author-email: json.yung@gmail.com, tr.trojo@gmail.com
License: MIT
Classifier: Development Status :: 3 - Alpha
Classifier: Intended Audience :: Developers
Classifier: Topic :: Utilities
Classifier: License :: OSI Approved :: MIT License
Classifier: Programming Language :: Python :: 3
Classifier: Development Status :: 3 - Alpha
Classifier: Intended Audience :: Developers
Classifier: Operating System :: OS Independent
Classifier: Programming Language :: Python :: 3.9
Classifier: License :: OSI Approved :: MIT License
License-File: LICENSE
